passwordtools/__init__.py
passwordtools/main.py
passwordtools_yt-0.2.5.dist-info/LICENCE
passwordtools_yt-0.2.5.dist-info/METADATA
passwordtools_yt-0.2.5.dist-info/WHEEL
passwordtools_yt-0.2.5.dist-info/top_level.txt
passwordtools_yt-0.2.5.dist-info/RECORD
